data_structures/__init__.py
data_structures/graphs/__init__.py
data_structures/graphs/edge.py
data_structures/graphs/graph.py
data_structures/graphs/vertex.py
data_structures/linear/__init__.py
data_structures/linear/list_node.py
data_structures/linear/lists/__init__.py
data_structures/linear/lists/linked_list.py
data_structures/linear/queues/__init__.py
data_structures/linear/queues/array_queue.py
data_structures/linear/queues/linked_queue.py
data_structures/linear/stacks/__init__.py
data_structures/linear/stacks/array_stack.py
data_structures/linear/stacks/array_stack_generics.py
data_structures/linear/stacks/linked_stack.py
data_structures/linear/util.py
data_structures/maps_dicts_hash/__init__.py
data_structures/maps_dicts_hash/chain_hashmap.py
data_structures/maps_dicts_hash/hashmap_base.py
data_structures/maps_dicts_hash/map_base.py
data_structures/maps_dicts_hash/probe_hashmap.py
data_structures/maps_dicts_hash/unsorted_table_map.py
data_structures/priority_queues/__init__.py
data_structures/priority_queues/array_heap.py
data_structures/priority_queues/priority_queue_base.py
data_structures/search_trees/__init__.py
data_structures/search_trees/linked_binary_search_tree.py
data_structures/trees/__init__.py
data_structures/trees/binary_tree_node.py
data_structures/trees/linked_binary_tree.py
python_ed_fcad_uner-0.1.1.dist-info/licenses/LICENSE
python_ed_fcad_uner-0.1.1.dist-info/METADATA
python_ed_fcad_uner-0.1.1.dist-info/WHEEL
python_ed_fcad_uner-0.1.1.dist-info/RECORD
