Metadata-Version: 2.4
Name: python-ed-fcad-uner
Version: 0.1.1
Summary: Paquete de implementación de estructuras de datos para la asignatura de Programación III de la FCAD-UNER
License: GPL-3.0-or-later
License-File: LICENSE
Keywords: data_structures,python,data structures,graph,trees,stack,queue,pilas,colas,árboles
Author: Nacho Novello
Author-email: ignacio.novello@uner.edu.ar
Requires-Python: >=3.10
Classifier: License :: OSI Approved :: GNU General Public License v3 or later (GPLv3+)
Classifier: Programming Language :: Python :: 3
Classifier: Programming Language :: Python :: 3.10
Classifier: Programming Language :: Python :: 3.11
Classifier: Programming Language :: Python :: 3.12
Classifier: Programming Language :: Python :: 3.13
Classifier: Programming Language :: Python :: 3.14
Project-URL: Repository, https://github.com/nachonovello1984/python_ed_fcad_uner
